geometamaker/__init__.py
geometamaker/cli.py
geometamaker/config.py
geometamaker/geometamaker.py
geometamaker/models.py
geometamaker/utils.py
geometamaker-0.2.0.dist-info/licenses/LICENSE.txt
geometamaker-0.2.0.dist-info/METADATA
geometamaker-0.2.0.dist-info/WHEEL
geometamaker-0.2.0.dist-info/entry_points.txt
geometamaker-0.2.0.dist-info/top_level.txt
geometamaker-0.2.0.dist-info/RECORD
