Metadata-Version: 2.4
Name: geometamaker
Version: 0.2.0
Summary: metadata creation for geospatial data
Maintainer: Natural Capital Project Software Team
License: 
Keywords: gis,geospatial,metadata
Classifier: Intended Audience :: Developers
Classifier: Development Status :: 3 - Alpha
Classifier: Intended Audience :: Science/Research
Classifier: Natural Language :: English
Classifier: Operating System :: MacOS :: MacOS X
Classifier: Operating System :: Microsoft
Classifier: Operating System :: POSIX
Classifier: Programming Language :: Python :: 3
Classifier: Programming Language :: Python :: 3.9
Classifier: Programming Language :: Python :: 3.10
Classifier: Programming Language :: Python :: 3.11
Classifier: Programming Language :: Python :: 3.12
Classifier: Programming Language :: Python :: 3.13
Classifier: License :: OSI Approved :: Apache Software License
Classifier: Topic :: Scientific/Engineering :: GIS
Requires-Python: >=3.9
License-File: LICENSE.txt
Requires-Dist: aiohttp
Requires-Dist: click
Requires-Dist: fsspec
Requires-Dist: GDAL
Requires-Dist: frictionless>=5.10.0
Requires-Dist: numpy
Requires-Dist: platformdirs
Requires-Dist: Pydantic>=2.0
Requires-Dist: pygeoprocessing>=2.4.5
Requires-Dist: pyyaml
Requires-Dist: requests
Dynamic: license-file
